{
    "1": {
        "Rating": "Mature",
        "Archive Warnings": "Graphic Depictions Of Violence",
        "Category": "Gen",
        "Fandom": [
            "",
            "Private Nightmares | Project Ghostlight",
            "Candela Obscura (Critical Role Web Series)"
        ],
        "Characters": [
            "",
            "Katie (Private Nightmares)",
            "Gable (Private Nightmares)",
            "Jade (Private Nightmares)",
            "Eddie (Private Nightmares)",
            "Naomi (Private Nightmares)",
            "Robert (Private Nightmares)",
            "Malcom Trills (Candela Obscura)",
            "Edgar Lycoris",
            "Horatio (Private Nightmares)",
            "Vulo (Private Nightmares)",
            "Manny (Private Nightmares)",
            "Cosmo Grimm (Candela Obscura)"
        ],
        "Relationships": [
            "",
            "Eddie & Katie (Private Nightmares)",
            "Naomi & Jade (Private Nightmares)",
            "Eddie & Jade (Private Nightmares)",
            "Gable & Jade (Private Nightmares)"
        ],
        "Additional Tags": [
            "",
            "Vampires",
            "Gaslamp Fantasy",
            "Horror",
            "Monster - Freeform",
            "Blood",
            "Body Horror",
            "Autopsy",
            "Mystery",
            "don't look too hard at the Candela timeline"
        ],
        "Language": "English",
        "Is Series": false,
        "Date Published": "2026-03-04",
        "Date Updated": "2026-05-12",
        "Word Count": 14223,
        "Chapter Count": "2/?",
        "Comment Count": 4,
        "Kudos Count": 6,
        "Bookmarks Count": 2
    },
    "2": {
        "Rating": "Unknown",
        "Archive Warnings": "No warnings listed",
        "Category": "Unknown",
        "Fandom": "No fandoms listed",
        "Characters": "No characters listed",
        "Relationships": "No relationships listed",
        "Additional Tags": "No additional tags",
        "Language": "Unknown",
        "Is Series": null,
        "Date Published": "Unknown",
        "Date Updated": "Unknown",
        "Word Count": "Unknown",
        "Chapter Count": "1",
        "Comment Count": 0,
        "Kudos Count": 0,
        "Bookmarks Count": 0
    },
    "3": {
        "Rating": "Unknown",
        "Archive Warnings": "No warnings listed",
        "Category": "Unknown",
        "Fandom": "No fandoms listed",
        "Characters": "No characters listed",
        "Relationships": "No relationships listed",
        "Additional Tags": "No additional tags",
        "Language": "Unknown",
        "Is Series": null,
        "Date Published": "Unknown",
        "Date Updated": "Unknown",
        "Word Count": "Unknown",
        "Chapter Count": "1",
        "Comment Count": 0,
        "Kudos Count": 0,
        "Bookmarks Count": 0
    },
    "4": {
        "Rating": "Unknown",
        "Archive Warnings": "No warnings listed",
        "Category": "Unknown",
        "Fandom": "No fandoms listed",
        "Characters": "No characters listed",
        "Relationships": "No relationships listed",
        "Additional Tags": "No additional tags",
        "Language": "Unknown",
        "Is Series": null,
        "Date Published": "Unknown",
        "Date Updated": "Unknown",
        "Word Count": "Unknown",
        "Chapter Count": "1",
        "Comment Count": 0,
        "Kudos Count": 0,
        "Bookmarks Count": 0
    },
    "5": {
        "Rating": "Teen And Up Audiences",
        "Archive Warnings": "No Archive Warnings Apply",
        "Category": "Gen",
        "Fandom": [
            "",
            "Candela Obscura (Critical Role Web Series)"
        ],
        "Characters": [
            "",
            "Grimoria (Candela Obscura)",
            "Leo Amicus",
            "Malcolm Trills",
            "Edgar Lycoris"
        ],
        "Relationships": [
            "",
            "Grimoria & Malcolm Trills",
            "Leo Amicus & Grimoria",
            "Grimoria & Edgar Lycoris",
            "Leo Amicus & Grimoria & Edgar Lycoris & Malcolm Trills"
        ],
        "Additional Tags": [
            "",
            "Hurt/Comfort",
            "Sickfic",
            "Neglect",
            "the foggs suck",
            "but grim's three self-appointed dads are there for her",
            "Found Family",
            "Fluff and Angst",
            "But mostly fluff",
            "Pneumonia",
            "Circle of the Crimson Mirror (Candela Obscura)",
            "Pre-Canon"
        ],
        "Language": "English",
        "Is Series": false,
        "Date Published": "2025-11-20",
        "Date Updated": "2026-01-17",
        "Word Count": 6155,
        "Chapter Count": "2/2",
        "Comment Count": 11,
        "Kudos Count": 22,
        "Bookmarks Count": 5
    },
    "6": {
        "Rating": "General Audiences",
        "Archive Warnings": "Creator Chose Not To Use Archive Warnings",
        "Category": "Gen",
        "Fandom": [
            "",
            "Candela Obscura (Critical Role Web Series)"
        ],
        "Characters": [
            "",
            "Oscar Grimm",
            "Cosmo Grimm (Candela Obscura)"
        ],
        "Relationships": [
            "",
            "Cosmo Grimm & Oscar Grimm"
        ],
        "Additional Tags": [
            "",
            "Hurt/Comfort",
            "Angst",
            "Complicated Relationships",
            "Family Feels",
            "Family Bonding",
            "Family Issues",
            "Immortality",
            "Parent-Child Relationship",
            "Temporary Character Death",
            "Canon Temporary Character Death"
        ],
        "Language": "English",
        "Is Series": false,
        "Date Published": "2024-06-11",
        "Date Updated": "2026-01-10",
        "Word Count": 64596,
        "Chapter Count": "28/28",
        "Comment Count": 26,
        "Kudos Count": 20,
        "Bookmarks Count": 2
    },
    "7": {
        "Rating": "Explicit",
        "Archive Warnings": "No Archive Warnings Apply",
        "Category": "/tags/M*s*M/works\">M/M",
        "Fandom": [
            "",
            "Candela Obscura (Critical Role Web Series)"
        ],
        "Characters": [
            "",
            "Marion Collodi",
            "Sean Finnerty (Candela Obscura)"
        ],
        "Relationships": [
            "",
            "Marion Collodi/Sean Finnerty"
        ],
        "Additional Tags": [
            "",
            "Light Bondage",
            "Rough Oral Sex",
            "Anal Sex",
            "Switching",
            "Missing Scene",
            "Podfic Welcome"
        ],
        "Language": "English",
        "Is Series": false,
        "Date Published": "2025-12-16",
        "Date Updated": "2025-12-16",
        "Word Count": 1834,
        "Chapter Count": "1/1",
        "Comment Count": 4,
        "Kudos Count": 11,
        "Bookmarks Count": 1
    },
    "8": {
        "Rating": "Explicit",
        "Archive Warnings": "No Archive Warnings Apply",
        "Category": "/tags/M*s*M/works\">M/M",
        "Fandom": [
            "",
            "Candela Obscura (Critical Role Web Series)"
        ],
        "Characters": [
            "",
            "Leo Amicus",
            "Original Male Character(s)"
        ],
        "Relationships": [
            "",
            "Leo Amicus/Original Character(s)"
        ],
        "Additional Tags": [
            "",
            "Circle of the Crimson Mirror (Candela Obscura)",
            "Boats and Ships",
            "Crew of the Dandridge",
            "Missing Scene",
            "Blow Jobs",
            "Anal Sex",
            "Topping from the Bottom",
            "Plot What Plot/Porn Without Plot",
            "almost",
            "Age Difference"
        ],
        "Language": "English",
        "Is Series": false,
        "Date Published": "2025-11-09",
        "Date Updated": "2025-11-09",
        "Word Count": 1070,
        "Chapter Count": "1/2",
        "Comment Count": 2,
        "Kudos Count": 2,
        "Bookmarks Count": 0
    },
    "9": {
        "Rating": "Unknown",
        "Archive Warnings": "No warnings listed",
        "Category": "Unknown",
        "Fandom": "No fandoms listed",
        "Characters": "No characters listed",
        "Relationships": "No relationships listed",
        "Additional Tags": "No additional tags",
        "Language": "Unknown",
        "Is Series": null,
        "Date Published": "Unknown",
        "Date Updated": "Unknown",
        "Word Count": "Unknown",
        "Chapter Count": "1",
        "Comment Count": 0,
        "Kudos Count": 0,
        "Bookmarks Count": 0
    },
    "10": {
        "Rating": "Unknown",
        "Archive Warnings": "No warnings listed",
        "Category": "Unknown",
        "Fandom": "No fandoms listed",
        "Characters": "No characters listed",
        "Relationships": "No relationships listed",
        "Additional Tags": "No additional tags",
        "Language": "Unknown",
        "Is Series": null,
        "Date Published": "Unknown",
        "Date Updated": "Unknown",
        "Word Count": "Unknown",
        "Chapter Count": "1",
        "Comment Count": 0,
        "Kudos Count": 0,
        "Bookmarks Count": 0
    },
    "11": {
        "Rating": "General Audiences",
        "Archive Warnings": "No Archive Warnings Apply",
        "Category": "/tags/F*s*M/works\">F/MGen",
        "Fandom": [
            "",
            "Horizon (Video Games)",
            "Red Dead Redemption (Video Games)",
            "Mortal Kombat (Video Games 2023-)",
            "Ghost of Tsushima (Video Game)",
            "League of Legends",
            "Candela Obscura (Critical Role Web Series)",
            "Star Wars: Jedi: Fallen Order Series (Video Games)",
            "Star Wars: The Bad Batch (Cartoon)",
            "Marvel's Spider-Man (Insomniac Games Video Games)",
            "Sekiro: Shadows Die Twice (Video Game)",
            "Cyberpunk 2077 (Video Game)"
        ],
        "Characters": [
            "",
            "Aloy (Horizon)",
            "Kotallo (Horizon)",
            "Charles Smith (Red Dead Redemption)",
            "Rain - Character",
            "Straw Hats (Ghost of Tsushima)",
            "Yone (League of Legends)",
            "Elsie Roberts (Candela Obscura)",
            "Rajan Savarimuthu",
            "Bode Akuna",
            "Kata Akuna",
            "Edmon Rampart",
            "Quentin Beck",
            "Sekiro | Wolf",
            "Sandayu Oda"
        ],
        "Relationships": [
            "",
            "Aloy/Kotallo (Horizon)",
            "Elsie Roberts/Rajan Savarimuthu",
            "Bode Akuna & Kata Akuna"
        ],
        "Additional Tags": [
            "",
            "Alternate Universe",
            "Crossover",
            "Gift Fic",
            "Birthday Party",
            "Rene de la Fontaine (Thresher)",
            "Black Hand Riku (Ghost of Tsushima)",
            "Only Partially Beta Read We Die Like [DATA CORRUPTED]",
            "Real Life Human",
            "Noshir Dalal - Freeform",
            "King Menace",
            "Sorry if I Got Any of These Characterizations Wrong",
            "Not An Extensive List"
        ],
        "Language": "English",
        "Is Series": false,
        "Date Published": "2025-08-15",
        "Date Updated": "2025-08-15",
        "Word Count": 2448,
        "Chapter Count": "1/1",
        "Comment Count": 7,
        "Kudos Count": 10,
        "Bookmarks Count": 1
    },
    "12": {
        "Rating": "General Audiences",
        "Archive Warnings": "No Archive Warnings Apply",
        "Category": "Gen",
        "Fandom": [
            "",
            "Candela Obscura (Critical Role Web Series)",
            "Candela Obscura (Roleplaying Game)"
        ],
        "Characters": [
            "",
            "Original Male Character(s)",
            "Cian\u00e1n Fedils\u00ed"
        ],
        "Relationships": "No relationships listed",
        "Additional Tags": [
            "",
            "Letters",
            "post investigation",
            "Irish Language"
        ],
        "Language": "English",
        "Is Series": false,
        "Date Published": "2025-08-04",
        "Date Updated": "2025-08-04",
        "Word Count": 148,
        "Chapter Count": "1/1",
        "Comment Count": 1,
        "Kudos Count": 2,
        "Bookmarks Count": 0
    },
    "13": {
        "Rating": "Mature",
        "Archive Warnings": "No Archive Warnings Apply",
        "Category": "/tags/Multi/works\">Multi",
        "Fandom": [
            "",
            "Candela Obscura (Critical Role Web Series)"
        ],
        "Characters": [
            "",
            "Jinnah \"Jean\" Basar",
            "Marion Collodi",
            "Sean Finnerty (Candela Obscura)",
            "Beatrix Monroe | Auntie Bee",
            "Gertie and Matilda the Chickens"
        ],
        "Relationships": [
            "",
            "Jinnah \"Jean\" Basar/Marion Collodi/Sean Finnerty",
            "Jinnah \"Jean\" Basar/Marion Collodi",
            "Marion Collodi & Sean Finnerty"
        ],
        "Additional Tags": [
            "",
            "Post-Canon Fix-It",
            "Post-Canon",
            "POV Alternating",
            "POV Third Person",
            "Sean and Marion love each other more than anything their relationship is just not sexual",
            "Soulmates",
            "OT3",
            "OT3 being forged before your very eyes",
            "Developing Relationship",
            "Everybody Lives",
            "Marion is full of love",
            "Sean if full of doubt",
            "Jean is full of DETERMINATION"
        ],
        "Language": "English",
        "Is Series": false,
        "Date Published": "2024-10-16",
        "Date Updated": "2025-07-16",
        "Word Count": 10107,
        "Chapter Count": "11/11",
        "Comment Count": 49,
        "Kudos Count": 51,
        "Bookmarks Count": 2
    },
    "14": {
        "Rating": "Explicit",
        "Archive Warnings": "No Archive Warnings Apply",
        "Category": "/tags/M*s*M/works\">M/M",
        "Fandom": [
            "",
            "Candela Obscura (Critical Role Web Series)"
        ],
        "Characters": [
            "",
            "Sean Finnerty (Candela Obscura)",
            "Nathaniel Trapp",
            "Jane Windermere",
            "Anthony Finnerty (Candela Obscura)",
            "Jimmy Finnerty (Candela Obscura)",
            "Margaret \"Peggy\" Finnerty (Candela Obscura)"
        ],
        "Relationships": [
            "",
            "Sean Finnerty/Nathaniel Trapp",
            "Anthony Finnerty/Jane Windermere"
        ],
        "Additional Tags": [
            "",
            "Alternate Universe - Canon Divergence",
            "Circle of Needle and Thread (Candela Obscura)",
            "Arranged Marriage",
            "Dom/sub",
            "No Candela",
            "No NoMAD",
            "Coming Out",
            "Closeted Character",
            "Size Kink",
            "Large Cock",
            "Smut",
            "Sex Club",
            "Cheating",
            "Nathaniel Trapp has a Big Dick",
            "Dom Nathaniel Trapp (Candela Obscura)",
            "Sub Sean Finnerty (Candela Obscura)",
            "Push-Ups",
            "Anal Sex",
            "Aftercare",
            "Light Angst"
        ],
        "Language": "English",
        "Is Series": false,
        "Date Published": "2024-04-11",
        "Date Updated": "2025-06-15",
        "Word Count": 5978,
        "Chapter Count": "3/?",
        "Comment Count": 17,
        "Kudos Count": 34,
        "Bookmarks Count": 0
    },
    "15": {
        "Rating": "Mature",
        "Archive Warnings": "No Archive Warnings Apply",
        "Category": "/tags/F*s*M/works\">F/M",
        "Fandom": [
            "",
            "Candela Obscura (Critical Role Web Series)"
        ],
        "Characters": [
            "",
            "Nathaniel Trapp",
            "Jinnah \"Jean\" Basar",
            "Beatrix Monroe | Auntie Bee",
            "Lucas Suarez (Candela Obscura)"
        ],
        "Relationships": [
            "",
            "Jinnah \"Jean\" Basar/Nathaniel Trapp",
            "Implied Past Jinnah \u201cJean\u201d Basar/Marion Collodi",
            "Implied Past Marion Collodi/Sean Finnerty/Nathaniel Trapp"
        ],
        "Additional Tags": [
            "",
            "Post Series",
            "Canon Compliant"
        ],
        "Language": "English",
        "Is Series": false,
        "Date Published": "2025-05-29",
        "Date Updated": "2025-05-29",
        "Word Count": 4748,
        "Chapter Count": "1/1",
        "Comment Count": 6,
        "Kudos Count": 10,
        "Bookmarks Count": 4
    },
    "16": {
        "Rating": "Unknown",
        "Archive Warnings": "No warnings listed",
        "Category": "Unknown",
        "Fandom": "No fandoms listed",
        "Characters": "No characters listed",
        "Relationships": "No relationships listed",
        "Additional Tags": "No additional tags",
        "Language": "Unknown",
        "Is Series": null,
        "Date Published": "Unknown",
        "Date Updated": "Unknown",
        "Word Count": "Unknown",
        "Chapter Count": "1",
        "Comment Count": 0,
        "Kudos Count": 0,
        "Bookmarks Count": 0
    },
    "17": {
        "Rating": "Mature",
        "Archive Warnings": "Major Character Death",
        "Category": "/tags/Multi/works\">Multi",
        "Fandom": [
            "",
            "Candela Obscura (Critical Role Web Series)"
        ],
        "Characters": [
            "",
            "Jinnah \"Jean\" Basar",
            "Marion Collodi",
            "Sean Finnerty (Candela Obscura)"
        ],
        "Relationships": [
            "",
            "Jinnah \"Jean\" Basar/Marion Collodi/Sean Finnerty"
        ],
        "Additional Tags": [
            "",
            "Post-Finale",
            "Dreams vs. Reality",
            "Ghosts"
        ],
        "Language": "English",
        "Is Series": false,
        "Date Published": "2025-01-07",
        "Date Updated": "2025-01-07",
        "Word Count": 8059,
        "Chapter Count": "1/1",
        "Comment Count": 22,
        "Kudos Count": 68,
        "Bookmarks Count": 6
    },
    "18": {
        "Rating": "Mature",
        "Archive Warnings": "No Archive Warnings Apply",
        "Category": "/tags/M*s*M/works\">M/M",
        "Fandom": [
            "",
            "Candela Obscura (Critical Role Web Series)"
        ],
        "Characters": [
            "",
            "Sean Finnerty (Candela Obscura)",
            "Nathaniel Trapp",
            "Beatrix Monroe | Auntie Bee",
            "Marion Collodi",
            "Jinnah \"Jean\" Basar"
        ],
        "Relationships": [
            "",
            "Sean Finnerty/Nathaniel Trapp"
        ],
        "Additional Tags": [
            "",
            "Alternate Universe - Canon Divergence",
            "Whump",
            "Gunshot Wounds",
            "Blood and Injury",
            "The inherent homoeroticism of wound tending",
            "Not Beta Read"
        ],
        "Language": "English",
        "Is Series": false,
        "Date Published": "2024-11-25",
        "Date Updated": "2024-11-25",
        "Word Count": 4280,
        "Chapter Count": "1/1",
        "Comment Count": 9,
        "Kudos Count": 68,
        "Bookmarks Count": 7
    },
    "19": {
        "Rating": "Unknown",
        "Archive Warnings": "No warnings listed",
        "Category": "Unknown",
        "Fandom": "No fandoms listed",
        "Characters": "No characters listed",
        "Relationships": "No relationships listed",
        "Additional Tags": "No additional tags",
        "Language": "Unknown",
        "Is Series": null,
        "Date Published": "Unknown",
        "Date Updated": "Unknown",
        "Word Count": "Unknown",
        "Chapter Count": "1",
        "Comment Count": 0,
        "Kudos Count": 0,
        "Bookmarks Count": 0
    },
    "20": {
        "Rating": "Explicit",
        "Archive Warnings": "No Archive Warnings Apply",
        "Category": "/tags/F*s*M/works\">F/M",
        "Fandom": [
            "",
            "Candela Obscura (Critical Role Web Series)"
        ],
        "Characters": [
            "",
            "Lester Shaw",
            "Evelyn White (Candela Obscura)",
            "Jacqueline \"Jackie\" Renoux",
            "Chey Tanii Mcheza"
        ],
        "Relationships": [
            "",
            "Lester Shaw/Evelyn White",
            "Chey Tanii Mcheza/Jackie Renoux"
        ],
        "Additional Tags": [
            "",
            "Tags May Change",
            "Other Additional Tags to Be Added",
            "Vaginal Sex",
            "Vaginal Fingering",
            "Oral Sex",
            "Plot What Plot/Porn Without Plot",
            "Self-Hatred",
            "Non-Consensual Voyeurism",
            "Discussion of Abortion",
            "Unprotected Sex",
            "Not Beta Read",
            "Erotic Horror",
            "monster fucking"
        ],
        "Language": "English",
        "Is Series": false,
        "Date Published": "2024-06-21",
        "Date Updated": "2024-09-24",
        "Word Count": 3775,
        "Chapter Count": "2/?",
        "Comment Count": 0,
        "Kudos Count": 10,
        "Bookmarks Count": 1
    },
    "21": {
        "Rating": "Teen And Up Audiences",
        "Archive Warnings": "No Archive Warnings Apply",
        "Category": "/tags/M*s*M/works\">M/M/tags/Multi/works\">Multi/tags/Other/works\">Other",
        "Fandom": [
            "",
            "Candela Obscura (Critical Role Web Series)"
        ],
        "Characters": [
            "",
            "Leo Amicus",
            "Rajan Savarimuthu",
            "Grimoria (Candela Obscura)",
            "Original Male Character(s)",
            "Nokari (Candela Obscura)",
            "Gadot",
            "Aadtika Savarimuthu",
            "Felix (Candela Obscura)"
        ],
        "Relationships": [
            "",
            "Leo Amicus/Original character",
            "Rajan Savarimuthu/Original Character(s)"
        ],
        "Additional Tags": [
            "",
            "Slow Burn",
            "Body Horror",
            "Bugs & Insects",
            "Eventual Smut",
            "Eventual Romance",
            "Wet Dream",
            "Does Oliver count as widowed",
            "he acts like one",
            "no beta we die like the circle of tide and bone",
            "circle of tide and bone spoilers",
            "circle of crimson mirror spoilers",
            "Sequel",
            "Slow start to this one",
            "Shameless Smut"
        ],
        "Language": "English",
        "Is Series": false,
        "Date Published": "2024-06-24",
        "Date Updated": "2024-09-16",
        "Word Count": 14095,
        "Chapter Count": "5/?",
        "Comment Count": 3,
        "Kudos Count": 2,
        "Bookmarks Count": 0
    },
    "22": {
        "Rating": "Explicit",
        "Archive Warnings": "No Archive Warnings Apply",
        "Category": "/tags/F*s*M/works\">F/M/tags/M*s*M/works\">M/M/tags/Multi/works\">Multi",
        "Fandom": [
            "",
            "Candela Obscura (Critical Role Web Series)"
        ],
        "Characters": [
            "",
            "Nathaniel Trapp",
            "Jinnah \"Jean\" Basar",
            "Marion Collodi",
            "Sean Finnerty (Candela Obscura)"
        ],
        "Relationships": [
            "",
            "Jinnah \"Jean\" Basar/Marion Collodi/Sean Finnerty/Nathaniel Trapp",
            "Jinnah \"Jean\" Basar/Marion Collodi",
            "Marion Collodi/Sean Finnerty",
            "Sean Finnerty/Nathaniel Trapp",
            "Marion Collodi/Sean Finnerty/Nathaniel Trapp",
            "Jinnah \"Jean\" Basar/Marion Collodi/Sean Finnerty",
            "Jinnah \"Jean\" Basar/Nathaniel Trapp"
        ],
        "Additional Tags": [
            "",
            "POV Nathaniel Trapp",
            "Plot What Plot/Porn Without Plot",
            "Master/Pet",
            "Consensual Kink",
            "Dom/sub",
            "Breeding",
            "a bit - Freeform",
            "Foursome - F/M/M/M",
            "Dom Nathaniel Trapp",
            "Dom Jinnah \"Jean\" Basar",
            "Sub Sean Finnerty (Candela Obscura)",
            "Sub Marion Collodi",
            "Sean Finnerty Has A Praise Kink",
            "Praise Kink",
            "Sexual Roleplay",
            "Collars",
            "Anal Sex",
            "Vaginal Sex",
            "it's pet play! what more do you want!",
            "no beta we die like sean finnerty",
            "Puppy Play"
        ],
        "Language": "English",
        "Is Series": false,
        "Date Published": "2024-08-30",
        "Date Updated": "2024-08-30",
        "Word Count": 3534,
        "Chapter Count": "1/1",
        "Comment Count": 2,
        "Kudos Count": 23,
        "Bookmarks Count": 0
    }
}